System-stubs/Collections.pyi
System-stubs/ComponentModel.pyi
System-stubs/Data.pyi
System-stubs/Globalization.pyi
System-stubs/IO.pyi
System-stubs/Reflection.pyi
System-stubs/__init__.pyi
System-stubs/Configuration/Assemblies.pyi
System-stubs/Configuration/__init__.pyi
System-stubs/Runtime/CompilerServices.pyi
System-stubs/Runtime/InteropServices.pyi
System-stubs/Runtime/Remoting.pyi
System-stubs/Runtime/Serialization.pyi
System-stubs/Runtime/__init__.pyi
System-stubs/Security/Policy.pyi
System-stubs/Security/__init__.pyi
System-stubs/Security/AccessControl/__init__.pyi
System-stubs/Security/Cryptography/__init__.pyi
System-stubs/Security/Cryptography/X509Certificates/__init__.pyi
System-stubs/Security/Principal/__init__.pyi
System-stubs/Threading/Tasks.pyi
System-stubs/Threading/__init__.pyi
System-stubs/Xml/Schema.pyi
System-stubs/Xml/Serialization.pyi
System-stubs/Xml/__init__.pyi
dotnet_stub_builder/__init__.py
dotnet_stub_builder/__main__.py
dotnet_stub_builder/makers.py
dotnet_stub_builder/type_conversion.py
dotnet_stub_builder/utils.py
dotnet_stubs-0.0.12.dist-info/LICENSE
dotnet_stubs-0.0.12.dist-info/METADATA
dotnet_stubs-0.0.12.dist-info/WHEEL
dotnet_stubs-0.0.12.dist-info/top_level.txt
dotnet_stubs-0.0.12.dist-info/RECORD
