Metadata-Version: 2.1
Name: dotnet-stubs
Version: 0.0.12
Summary: Incomplete, and probably incorrect, stubs for .NET.
Home-page: https://github.com/domdfcoding/dotnet-stubs
Author: Dominic Davis-Foster
Author-email: dominic@davis-foster.co.uk
License: MIT License
Project-URL: Documentation, https://dotnet-stubs.readthedocs.io
Project-URL: Issue_Tracker, https://github.com/domdfcoding/dotnet-stubs/issues
Project-URL: Source_Code, https://github.com/domdfcoding/dotnet-stubs
Platform: Windows
Platform: macOS
Platform: Linux
Classifier: License :: OSI Approved :: MIT License
Classifier: Operating System :: OS Independent
Classifier: Programming Language :: Python
Classifier: Programming Language :: Python :: 3 :: Only
Classifier: Programming Language :: Python :: 3.6
Classifier: Programming Language :: Python :: Implementation :: CPython
Requires-Python: >=3.6
Provides-Extra: all
Requires-Dist: autoflake ; extra == 'all'
Requires-Dist: domdf-python-tools (>=0.7.0) ; extra == 'all'
Requires-Dist: isort (>=5.0.0) ; extra == 'all'
Requires-Dist: orderedset ; extra == 'all'
Requires-Dist: pythonnet ; extra == 'all'
Provides-Extra: builder
Requires-Dist: pythonnet ; extra == 'builder'
Requires-Dist: domdf-python-tools (>=0.7.0) ; extra == 'builder'
Requires-Dist: orderedset ; extra == 'builder'
Requires-Dist: isort (>=5.0.0) ; extra == 'builder'
Requires-Dist: autoflake ; extra == 'builder'
